[
    {
        "description": "System table containing logging entries with information about `BACKUP` and `RESTORE` operations.",
        "slug": "/en/operations/system-tables/backup_log",
        "title": "backup_log",
        "keywords": [
            "system table",
            "backup_log"
        ]
    },
    {
        "description": "System table containing active roles for the current user.",
        "slug": "/en/operations/system-tables/current-roles",
        "title": "current_roles",
        "keywords": [
            "system table",
            "current_roles"
        ]
    },
    {
        "description": "System table containing information about local files that are in the queue to be sent to the shards.",
        "slug": "/en/operations/system-tables/distribution_queue",
        "title": "distribution_queue",
        "keywords": [
            "system table",
            "distribution_queue"
        ]
    },
    {
        "description": "System table containing information about dictionaries",
        "slug": "/en/operations/system-tables/dictionaries",
        "title": "dictionaries",
        "keywords": [
            "system table",
            "dictionaries"
        ]
    },
    {
        "description": "System table containing metadata of each table that the server knows about.",
        "slug": "/en/operations/system-tables/tables",
        "title": "tables",
        "keywords": [
            "system table",
            "tables"
        ]
    },
    {
        "description": "System table containing information about resources residing on the local server with one row for every resource.",
        "slug": "/en/operations/system-tables/resources",
        "title": "resources",
        "keywords": [
            "system table",
            "resources"
        ]
    },
    {
        "description": "System table containing profiling information on the processors level (which can be found in `EXPLAIN PIPELINE`)",
        "slug": "/en/operations/system-tables/processors_profile_log",
        "title": "processors_profile_log",
        "keywords": [
            "system table",
            "processors_profile_log",
            "EXPLAIN PIPELINE"
        ]
    },
    {
        "slug": "/en/operations/system-tables/parts",
        "title": "parts",
        "keywords": [
            "system table",
            "parts"
        ]
    },
    {
        "description": "System table containing all active roles at the moment, including the current role of the current user and the granted roles for the current role",
        "slug": "/en/operations/system-tables/enabled-roles",
        "title": "enabled_roles",
        "keywords": [
            "system table",
            "enabled_roles"
        ]
    },
    {
        "description": "System table containing information about the dependent views executed when running a query, for example, the view type or the execution time.",
        "slug": "/en/operations/system-tables/query_views_log",
        "title": "query_views_log",
        "keywords": [
            "system table",
            "query_views_log"
        ]
    },
    {
        "description": "System table containing logging entries with information about various blob storage operations such as uploads and deletes.",
        "slug": "/en/operations/system-tables/blob_storage_log",
        "title": "blob_storage_log",
        "keywords": [
            "system table",
            "blob_storage_log"
        ]
    },
    {
        "description": "System table containing information about storage policies and volumes which are defined in server configuration.",
        "slug": "/en/operations/system-tables/storage_policies",
        "title": "storage_policies",
        "keywords": [
            "system table",
            "storage_policies"
        ]
    },
    {
        "description": "System table containing information about existing data skipping indices in all the tables.",
        "slug": "/en/operations/system-tables/data_skipping_indices",
        "title": "data_skipping_indices",
        "keywords": [
            "system table",
            "data_skipping_indices"
        ]
    },
    {
        "description": "System table containing information about session settings for current user.",
        "slug": "/en/operations/system-tables/settings",
        "title": "settings",
        "keywords": [
            "system table",
            "settings"
        ]
    },
    {
        "description": "System table containing descriptions of table engines supported by the server and the features they support.",
        "slug": "/en/operations/system-tables/table_engines",
        "title": "table_engines",
        "keywords": [
            "system table",
            "table_engines"
        ]
    },
    {
        "description": "System table used for implementing the `SHOW PROCESSLIST` query.",
        "slug": "/en/operations/system-tables/processes",
        "title": "processes",
        "keywords": [
            "system table",
            "processes"
        ]
    },
    {
        "description": "System table containing information about columns in all tables",
        "slug": "/en/operations/system-tables/columns",
        "title": "columns",
        "keywords": [
            "system table",
            "columns"
        ]
    },
    {
        "description": "System table containing formation about quota usage by the current user such as how much of the quota is used and how much is left.",
        "slug": "/en/operations/system-tables/quota_usage",
        "title": "quota_usage",
        "keywords": [
            "system table",
            "quota_usage"
        ]
    },
    {
        "description": "System table containing information about disks defined in the server configuration",
        "slug": "/en/operations/system-tables/disks",
        "title": "disks",
        "keywords": [
            "system table",
            "disks"
        ]
    },
    {
        "description": "System table containing information about parameters `graphite_rollup` which are used in tables with `GraphiteMergeTree` type engines.",
        "slug": "/en/operations/system-tables/graphite_retentions",
        "title": "graphite_retentions",
        "keywords": [
            "system table",
            "graphite_retentions"
        ]
    },
    {
        "description": "System table containing formation about quota usage by all users.",
        "slug": "/en/operations/system-tables/quotas_usage",
        "title": "quotas_usage",
        "keywords": [
            "system table",
            "quotas_usage",
            "quota"
        ]
    },
    {
        "description": "System table containing the role grants for users and roles.",
        "slug": "/en/operations/system-tables/role-grants",
        "title": "role_grants",
        "keywords": [
            "system table",
            "role_grants"
        ]
    },
    {
        "description": "System table containing information about async inserts. Each entry represents an insert query buffered into an async insert query.",
        "slug": "/en/operations/system-tables/asynchronous_insert_log",
        "title": "asynchronous_insert_log",
        "keywords": [
            "system table",
            "asynchronous_insert_log"
        ]
    },
    {
        "description": "System table containing information about trace spans for executed queries.",
        "slug": "/en/operations/system-tables/opentelemetry_span_log",
        "title": "opentelemetry_span_log",
        "keywords": [
            "system table",
            "opentelemetry_span_log"
        ]
    },
    {
        "description": "System table containing information about the settings of S3Queue tables. Available from server version `24.10`.",
        "slug": "/en/operations/system-tables/s3_queue_settings",
        "title": "s3_queue_settings",
        "keywords": [
            "system table",
            "s3_queue_settings"
        ]
    },
    {
        "description": "System table useful for C++ experts and ClickHouse engineers containing information for introspection of the `clickhouse` binary.",
        "slug": "/en/operations/system-tables/symbols",
        "title": "symbols",
        "keywords": [
            "system table",
            "symbols"
        ]
    },
    {
        "description": "System table containing information about distributed ddl queries (queries using the ON CLUSTER clause) that were executed on a cluster.",
        "slug": "/en/operations/system-tables/distributed_ddl_queue",
        "title": "distributed_ddl_queue",
        "keywords": [
            "system table",
            "distributed_ddl_queue"
        ]
    },
    {
        "description": "System database providing an almost standardized DBMS-agnostic view on metadata of database objects.",
        "slug": "/en/operations/system-tables/information_schema",
        "title": "INFORMATION_SCHEMA",
        "keywords": [
            "system database",
            "information_schema"
        ]
    },
    {
        "description": "System table containing information about and status of recent asynchronous jobs (e.g. for tables which are loading). The table contains a row for every job.",
        "slug": "/en/operations/system-tables/asynchronous_loader",
        "title": "asynchronous_loader",
        "keywords": [
            "system table",
            "asynchronous_loader"
        ]
    },
    {
        "description": "System table containing a list of database engines supported by the server.",
        "slug": "/en/operations/system-tables/database_engines",
        "title": "database_engines",
        "keywords": [
            "system table",
            "database_engines"
        ]
    },
    {
        "description": "System table containing information about quotas.",
        "slug": "/en/operations/system-tables/quotas",
        "title": "quotas",
        "keywords": [
            "system table",
            "quotas",
            "quota"
        ]
    },
    {
        "description": "System table containing information about detached parts of MergeTree tables",
        "slug": "/en/operations/system-tables/detached_parts",
        "title": "detached_parts",
        "keywords": [
            "system table",
            "detached_parts"
        ]
    },
    {
        "description": "System table containing information about the parameters of the request to the ZooKeeper server and the response from it.",
        "slug": "/en/operations/system-tables/zookeeper_log",
        "title": "zookeeper_log",
        "keywords": [
            "system table",
            "zookeeper_log"
        ]
    },
    {
        "description": "System table containing information about memory allocations done via jemalloc allocator in different size classes (bins) aggregated from all arenas.",
        "slug": "/en/operations/system-tables/jemalloc_bins",
        "title": "jemalloc_bins",
        "keywords": [
            "system table",
            "jemalloc_bins"
        ]
    },
    {
        "description": "System table containing information about cached DNS records.",
        "slug": "/en/operations/system-tables/dns_cache",
        "title": "dns_cache",
        "keywords": [
            "system table",
            "dns_cache"
        ]
    },
    {
        "description": "System table containing information about threads that execute queries, for example, thread name, thread start time, duration of query processing.",
        "slug": "/en/operations/system-tables/query_thread_log",
        "title": "query_thread_log",
        "keywords": [
            "system table",
            "query_thread_log"
        ]
    },
    {
        "description": "System table containing history of all latency buckets, periodically flushed to disk.",
        "slug": "/en/operations/system-tables/latency_log",
        "title": "latency_log"
    },
    {
        "description": "System table containing information about merges and part mutations currently in process for tables in the MergeTree family.",
        "slug": "/en/operations/system-tables/merges",
        "title": "merges",
        "keywords": [
            "system table",
            "merges"
        ]
    },
    {
        "description": "System table containing a history of memory and metric values from table `system.events` for individual queries, periodically flushed to disk.",
        "slug": "/en/operations/system-tables/query_metric_log",
        "title": "query_metric_log",
        "keywords": [
            "system table",
            "query_metric_log"
        ]
    },
    {
        "description": "System table containing information about settings of AzureQueue tables. Available from server version `24.10`.",
        "slug": "/en/operations/system-tables/azure_queue_settings",
        "title": "azure_queue_settings",
        "keywords": [
            "system table",
            "azure_queue_settings"
        ]
    },
    {
        "description": "System table containing information about all successful and failed login and logout events.",
        "slug": "/en/operations/system-tables/session_log",
        "title": "session_log",
        "keywords": [
            "system table",
            "session_log"
        ]
    },
    {
        "description": "System table containing information about and status of scheduling nodes residing on the local server.",
        "slug": "/en/operations/system-tables/scheduler",
        "title": "scheduler",
        "keywords": [
            "system table",
            "scheduler"
        ]
    },
    {
        "description": "System table containing error codes with the number of times they have been triggered.",
        "slug": "/en/operations/system-tables/errors",
        "title": "errors",
        "keywords": [
            "system table",
            "errors"
        ]
    },
    {
        "description": "System table containing licenses of third-party libraries that are located in the contrib directory of ClickHouse sources.",
        "slug": "/en/operations/system-tables/licenses",
        "title": "licenses",
        "keywords": [
            "system table",
            "licenses"
        ]
    },
    {
        "description": "System table containing information useful for an overview of memory usage and ProfileEvents of users.",
        "slug": "/en/operations/system-tables/user_processes",
        "title": "user_processes",
        "keywords": [
            "system table",
            "user_processes"
        ]
    },
    {
        "description": "System table containing information about currently running background fetches.",
        "slug": "/en/operations/system-tables/replicated_fetches",
        "title": "replicated_fetches",
        "keywords": [
            "system table",
            "replicated_fetches"
        ]
    },
    {
        "description": "System table containing information about supported data types",
        "slug": "/en/operations/system-tables/data_type_families",
        "title": "data_type_families",
        "keywords": [
            "system table",
            "data_type_families",
            "data types"
        ]
    },
    {
        "description": "System table containing information about existing projections in all tables.",
        "slug": "/en/operations/system-tables/projections",
        "title": "processors_profile_log",
        "keywords": [
            "system table",
            "projections"
        ]
    },
    {
        "description": "System table containing stack traces collected by the sampling query profiler.",
        "slug": "/en/operations/system-tables/trace_log",
        "title": "trace_log",
        "keywords": [
            "system table",
            "trace_log"
        ]
    },
    {
        "description": "System table containing information about configured roles.",
        "slug": "/en/operations/system-tables/roles",
        "title": "roles",
        "keywords": [
            "system table",
            "roles"
        ]
    },
    {
        "description": "System table containing a list of user accounts configured on the server.",
        "slug": "/en/operations/system-tables/users",
        "title": "users",
        "keywords": [
            "system table",
            "users"
        ]
    },
    {
        "description": "System table containing information about events that occurred with data parts in the MergeTree family tables, such as adding or merging of data.",
        "slug": "/en/operations/system-tables/part_log",
        "title": "part_log",
        "keywords": [
            "system table",
            "part_log"
        ]
    },
    {
        "description": "System table containing information about and status of replicated tables residing on the local server. Useful for monitoring.",
        "slug": "/en/operations/system-tables/replicas",
        "title": "replicas",
        "keywords": [
            "system table",
            "replicas"
        ]
    },
    {
        "description": "System table containing information about Refreshable Materialized Views.",
        "slug": "/en/operations/system-tables/view_refreshes",
        "title": "view_refreshes",
        "keywords": [
            "system table",
            "view_refreshes"
        ]
    },
    {
        "description": "System table containing information about tables that drop table has been executed on but for which data cleanup has not yet been performed",
        "slug": "/en/operations/system-tables/dropped_tables",
        "title": "dropped_tables",
        "keywords": [
            "system table",
            "dropped_tables"
        ]
    },
    {
        "description": "System table containing information about contributors.",
        "slug": "/en/operations/system-tables/contributors",
        "title": "contributors",
        "keywords": [
            "system table",
            "contributors"
        ]
    },
    {
        "description": "System table containing information about parts of MergeTree dropped tables from `system.dropped_tables`",
        "slug": "/en/operations/system-tables/dropped_tables_parts",
        "title": "dropped_tables_parts",
        "keywords": [
            "system table",
            "dropped_tables_parts"
        ]
    },
    {
        "description": "System table containing information about executed queries, for example, start time, duration of processing, error messages.",
        "slug": "/en/operations/system-tables/query_log",
        "title": "query_log",
        "keywords": [
            "system table",
            "query_log"
        ]
    },
    {
        "description": "System table containing logging entries.",
        "slug": "/en/operations/system-tables/text_log",
        "title": "text_log",
        "keywords": [
            "system table",
            "text_log"
        ]
    },
    {
        "description": "System table containing information about normal and aggregate functions.",
        "slug": "/en/operations/system-tables/functions",
        "title": "functions",
        "keywords": [
            "system table",
            "functions"
        ]
    },
    {
        "description": "System table containing historical values for `system.asynchronous_metrics`, which are saved once per time interval (one second by default)",
        "slug": "/en/operations/system-tables/asynchronous_metric_log",
        "title": "asynchronous_metric_log",
        "keywords": [
            "system table",
            "asynchronous_metric_log"
        ]
    },
    {
        "description": "System table containing information about in-progress data part moves of MergeTree tables. Each data part movement is represented by a single row.",
        "slug": "/en/operations/system-tables/moves",
        "title": "moves",
        "keywords": [
            "system table",
            "moves"
        ]
    },
    {
        "description": "System table containing information about bucket bounds used by `latency_log`.",
        "slug": "/en/operations/system-tables/latency_buckets",
        "title": "latency_buckets",
        "keywords": [
            "system table",
            "latency_buckets"
        ]
    },
    {
        "description": "System table containing information about the databases that are available to the current user.",
        "slug": "/en/operations/system-tables/databases",
        "title": "databases",
        "keywords": [
            "system table",
            "databases"
        ]
    },
    {
        "description": "System table containing information about maximums for all intervals of all quotas. Any number of rows or zero can correspond to one quota.",
        "slug": "/en/operations/system-tables/quota_limits",
        "title": "quota_limits",
        "keywords": [
            "system table",
            "quota_limits"
        ]
    },
    {
        "description": "System table containing metrics which can be calculated instantly, or have a current value.",
        "slug": "/en/operations/system-tables/metrics",
        "title": "metrics",
        "keywords": [
            "system table",
            "metrics"
        ]
    },
    {
        "description": "System table which shows the content of the query cache.",
        "slug": "/en/operations/system-tables/query_cache",
        "title": "query_cache",
        "keywords": [
            "system table",
            "query_cache"
        ]
    },
    {
        "description": "System table containing a single row with a single `dummy` UInt8 column containing the value 0. Similar to the `DUAL` table found in other DBMSs.",
        "slug": "/en/operations/system-tables/one",
        "title": "one",
        "keywords": [
            "system table",
            "one"
        ]
    },
    {
        "description": "System table containing information about pending asynchronous inserts in queue.",
        "slug": "/en/operations/system-tables/asynchronous_inserts",
        "title": "asynchronous_inserts",
        "keywords": [
            "system table",
            "asynchronous_inserts"
        ]
    },
    {
        "description": "System table containing a list of time zones that are supported by the ClickHouse server.",
        "slug": "/en/operations/system-tables/time_zones",
        "title": "time_zones",
        "keywords": [
            "system table",
            "time_zones"
        ]
    },
    {
        "description": "System table containing information about all cached file schemas.",
        "slug": "/en/operations/system-tables/schema_inference_cache",
        "title": "schema_inference_cache",
        "keywords": [
            "system table",
            "schema_inference_cache"
        ]
    },
    {
        "description": "System table similar to `system.numbers` but reads are parallelized and numbers can be returned in any order.",
        "slug": "/en/operations/system-tables/numbers_mt",
        "title": "numbers_mt",
        "keywords": [
            "system table",
            "numbers_mt"
        ]
    },
    {
        "description": "System table containing history of metrics values from tables `system.metrics` and `system.events`, periodically flushed to disk.",
        "slug": "/en/operations/system-tables/metric_log",
        "title": "metric_log",
        "keywords": [
            "system table",
            "metric_log"
        ]
    },
    {
        "description": "System table which describes the content of the settings profile: constraints, roles and users that the setting applies to, parent settings profiles.",
        "slug": "/en/operations/system-tables/settings_profile_elements",
        "title": "settings_profile_elements",
        "keywords": [
            "system table",
            "settings_profile_elements"
        ]
    },
    {
        "description": "System table containing formation about global settings for the server, which are specified in `config.xml`.",
        "slug": "/en/operations/system-tables/server_settings",
        "title": "server_settings",
        "keywords": [
            "system table",
            "server_settings"
        ]
    },
    {
        "description": "System table containing information about each detached table.",
        "slug": "/en/operations/system-tables/detached_tables",
        "title": "detached_tables",
        "keywords": [
            "system table",
            "detached_tables"
        ]
    },
    {
        "description": "System table containing filters for one particular table, as well as a list of roles and/or users which should use this row policy.",
        "slug": "/en/operations/system-tables/row_policies",
        "title": "row_policies",
        "keywords": [
            "system table",
            "row_policies"
        ]
    },
    {
        "description": "System table showing which privileges are granted to ClickHouse user accounts.",
        "slug": "/en/operations/system-tables/grants",
        "title": "grants",
        "keywords": [
            "system table",
            "grants"
        ]
    },
    {
        "description": "System table containing the history of error values from table `system.errors`, periodically flushed to disk.",
        "slug": "/en/operations/system-tables/error_log",
        "title": "error_log",
        "keywords": [
            "system table",
            "error_log"
        ]
    },
    {
        "description": "System table containing information about settings for MergeTree tables.",
        "slug": "/en/operations/system-tables/merge_tree_settings",
        "title": "merge_tree_settings",
        "keywords": [
            "system table",
            "merge_tree_settings"
        ]
    },
    {
        "description": "System table containing a single UInt64 column named `number` that contains almost all the natural numbers starting from zero.",
        "slug": "/en/operations/system-tables/numbers",
        "title": "numbers",
        "keywords": [
            "system table",
            "numbers"
        ]
    },
    {
        "description": "System table containing information about stack traces for fatal errors.",
        "slug": "/en/operations/system-tables/crash-log",
        "title": "crash_log",
        "keywords": [
            "system table",
            "crash_log"
        ]
    },
    {
        "description": "System table containing information for workloads residing on the local server.",
        "slug": "/en/operations/system-tables/workloads",
        "title": "workloads",
        "keywords": [
            "system table",
            "workloads"
        ]
    },
    {
        "description": "System table which contains stack traces of all server threads. Allows developers to introspect the server state.",
        "slug": "/en/operations/system-tables/stack_trace",
        "title": "stack_trace",
        "keywords": [
            "system table",
            "stack_trace"
        ]
    },
    {
        "description": "System table containing information about clusters available in the config file and the servers defined in them.",
        "slug": "/en/operations/system-tables/clusters",
        "title": "clusters",
        "keywords": [
            "system table",
            "clusters"
        ]
    },
    {
        "description": "System table containing information about the number of events that have occurred in the system.",
        "slug": "/en/operations/system-tables/events",
        "title": "events",
        "keywords": [
            "system table",
            "events"
        ]
    },
    {
        "description": "System table containing information about mutations of MergeTree tables and their progress. Each mutation command is represented by a single row.",
        "slug": "/en/operations/system-tables/mutations",
        "title": "mutations",
        "keywords": [
            "system table",
            "mutations"
        ]
    },
    {
        "description": "System table containing information about setting changes in previous ClickHouse versions.",
        "slug": "/en/operations/system-tables/settings_changes",
        "title": "settings_changes",
        "keywords": [
            "system table",
            "settings_changes"
        ]
    },
    {
        "description": "System table containing information about parts and columns of MergeTree tables.",
        "slug": "/en/operations/system-tables/parts_columns",
        "title": "parts_columns",
        "keywords": [
            "system table",
            "parts_columns"
        ]
    },
    {
        "description": "System table which exists only if ZooKeeper is configured. Shows current connections to ZooKeeper (including auxiliary ZooKeepers).",
        "slug": "/en/operations/system-tables/zookeeper_connection",
        "title": "zookeeper_connection",
        "keywords": [
            "system table",
            "zookeeper_connection"
        ]
    },
    {
        "description": "Contains queries used by `/dashboard` page accessible though the HTTP interface. useful for monitoring and troubleshooting.",
        "slug": "/en/operations/system-tables/dashboards",
        "title": "dashboards",
        "keywords": [
            "system table",
            "dashboards",
            "monitoring",
            "troubleshooting"
        ]
    },
    {
        "description": "System table containing information about ClickHouse server's build options.",
        "slug": "/en/operations/system-tables/build_options",
        "title": "build_options",
        "keywords": [
            "system table",
            "build_options"
        ]
    },
    {
        "description": "System table containing metrics that are calculated periodically in the background. For example, the amount of RAM in use.",
        "slug": "/en/operations/system-tables/asynchronous_metrics",
        "title": "asynchronous_metrics",
        "keywords": [
            "system table",
            "asynchronous_metrics"
        ]
    },
    {
        "description": "System table containing information about Kafka consumers.",
        "slug": "/en/operations/system-tables/kafka_consumers",
        "title": "kafka_consumers",
        "keywords": [
            "system table",
            "kafka_consumers"
        ]
    },
    {
        "description": "System table which contains properties of configured setting profiles.",
        "slug": "/en/operations/system-tables/settings_profiles",
        "title": "settings_profiles",
        "keywords": [
            "system table",
            "settings_profiles"
        ]
    },
    {
        "description": "System table which exists only if ClickHouse Keeper or ZooKeeper are configured. It exposes data from the Keeper cluster defined in the config.",
        "slug": "/en/operations/system-tables/zookeeper",
        "title": "zookeeper",
        "keywords": [
            "system table",
            "zookeeper"
        ]
    },
    {
        "description": "System table containing information about tasks from replication queues stored in ClickHouse Keeper, or ZooKeeper, for tables in the `ReplicatedMergeTree` family.",
        "slug": "/en/operations/system-tables/replication_queue",
        "title": "replication_queue",
        "keywords": [
            "system table",
            "replication_queue"
        ]
    }
]
